rockstarfoxdot/__init__.py
rockstarfoxdot-1.0.0.dist-info/LICENSE
rockstarfoxdot-1.0.0.dist-info/METADATA
rockstarfoxdot-1.0.0.dist-info/WHEEL
rockstarfoxdot-1.0.0.dist-info/top_level.txt
rockstarfoxdot-1.0.0.dist-info/RECORD
