Metadata-Version: 2.1
Name: rockstarfoxdot
Version: 1.0.0
Summary: Using using the RockStar EsoLang to make music in FoxDot 
Home-page: https://github.com/stretchyboy/rockstarfoxdot
Author: Martyn Eggleton
Author-email: martyn.eggleton@gmail.com
License: UNKNOWN
Platform: UNKNOWN
Classifier: Programming Language :: Python :: 3
Classifier: License :: OSI Approved :: MIT License
Classifier: Operating System :: OS Independent
